pympw
