Metadata-Version: 1.1
Name: pympw
Version: 0.2
Summary:  An implementation of the Master Password algorithm v3 with a nice CLI
Home-page: http://github.com/roguh/pympw
Author: Hugo Rivera
Author-email: flyingcircus@example.com
License: UNKNOWN
Platform: UNKNOWN
Classifier: Topic :: Security
Classifier: Topic :: Security :: Cryptography
Classifier: Topic :: Utilities
Classifier: Environment :: Console
Classifier: Operating System :: Unix
Classifier: Operating System :: POSIX :: Linux
Classifier: Topic :: Internet
